zoom_audio_transcribe/__init__.py
zoom_audio_transcribe/_repo_version.py
zoom_audio_transcribe/cli.py
zoom_audio_transcribe/convert.py
zoom_audio_transcribe/transcribe.py
zoom_audio_transcribe/model/Gr.fst
zoom_audio_transcribe/model/HCLr.fst
zoom_audio_transcribe/model/disambig_tid.int
zoom_audio_transcribe/model/final.mdl
zoom_audio_transcribe/model/mfcc.conf
zoom_audio_transcribe/model/word_boundary.int
zoom_audio_transcribe/model/ivector/final.dubm
zoom_audio_transcribe/model/ivector/final.ie
zoom_audio_transcribe/model/ivector/final.mat
zoom_audio_transcribe/model/ivector/global_cmvn.stats
zoom_audio_transcribe/model/ivector/online_cmvn.conf
zoom_audio_transcribe/model/ivector/splice.conf
zoom_audio_transcribe-0.1.1.dist-info/LICENSE
zoom_audio_transcribe-0.1.1.dist-info/METADATA
zoom_audio_transcribe-0.1.1.dist-info/WHEEL
zoom_audio_transcribe-0.1.1.dist-info/entry_points.txt
zoom_audio_transcribe-0.1.1.dist-info/top_level.txt
zoom_audio_transcribe-0.1.1.dist-info/RECORD
